unboring/__init__.py
unboring/input.py
unboring/number.py
unboring/regex.py
unboring/text.py
unboring-0.0.1.2.dist-info/LICENSE
unboring-0.0.1.2.dist-info/METADATA
unboring-0.0.1.2.dist-info/WHEEL
unboring-0.0.1.2.dist-info/top_level.txt
unboring-0.0.1.2.dist-info/RECORD
