Metadata-Version: 2.1
Name: unboring
Version: 0.0.1.2
Summary: Forget the small stuff. Why do repatitive things when its done for you.
Home-page: https://github.com/LeoGaunt/unboring
Author: Leo Gaunt
Author-email: leogaunt05@outlook.com
License: UNKNOWN
Project-URL: Bug Tracker, https://github.com/LeoGaunt/unboring/issues
Platform: UNKNOWN
Classifier: Programming Language :: Python :: 3
Classifier: License :: OSI Approved :: MIT License
Classifier: Operating System :: OS Independent
Requires-Python: >=3.6
License-File: LICENSE
